[
  {
    "id": 1,
    "name": "Ultra Hydrating Face Cream",
    "description": "A rich, moisturizing cream that keeps dry skin soft and supple.",
    "price": "₹799",
    "rating": 4.2,
    "image": "https://res.cloudinary.com/djbjfsshe/image/upload/v1747502347/oily1_uifsra.png",
    "category": "Normal Skin"
  },
  {
    "id": 2,
    "name": "Deep Nourishing Body Lotion",
    "description": "A body lotion infused with shea butter for long-lasting hydration.",
    "price": "₹499",
    "rating": 4.5,
    "image": "https://res.cloudinary.com/djbjfsshe/image/upload/v1747502372/oily2_p54dfq.png",
    "category": "Dry Skin"
  },
  {
    "id": 3,
    "name": "Gentle Hydrating Cleanser",
    "description": "A soap-free cleanser that gently removes impurities while keeping skin hydrated.",
    "price": "₹599",
    "rating": 4.3,
    "image": "https://res.cloudinary.com/djbjfsshe/image/upload/v1747502372/oily3_ngd1ag.png",
    "category": "Dry Skin"
  },
  {
    "id": 4,
    "name": "Overnight Repair Moisturizer",
    "description": "A night cream that restores moisture to your skin while you sleep.",
    "price": "₹899",
    "rating": 4.7,
    "image": "https://res.cloudinary.com/djbjfsshe/image/upload/v1747502374/oily4_bk9wtf.png",
    "category": "Dry Skin"
  },
  {
    "id": 5,
    "name": "Hydrating Sheet Mask",
    "description": "A sheet mask enriched with hyaluronic acid for instant hydration.",
    "price": "₹199",
    "rating": 4.4,
    "image": "https://res.cloudinary.com/djbjfsshe/image/upload/v1747502377/oily5_k4zibr.png",
    "category": "Dry Skin"
  },
  {
    "id": 6,
    "name": "Intense Moisturizing Hand Cream",
    "description": "A hand cream that soothes dry, cracked hands.",
    "price": "₹299",
    "rating": 4.6,
    "image": "https://res.cloudinary.com/djbjfsshe/image/upload/v1747502347/oily1_uifsra.png",
    "category": "Dry Skin"
  },
  {
    "id": 7,
    "name": "Balancing Face Cleanser",
    "description": "A gentle cleanser that balances oil and moisture for combination skin.",
    "price": "₹499",
    "rating": 4.4,
    "image": "https://res.cloudinary.com/djbjfsshe/image/upload/v1747502372/oily2_p54dfq.png",
    "category": "Combination Skin"
  },
  {
    "id": 8,
    "name": "Dual-Action Moisturizer",
    "description": "Moisturizes dry areas while controlling oil in the T-zone.",
    "price": "₹699",
    "rating": 4.8,
    "image": "https://res.cloudinary.com/djbjfsshe/image/upload/v1747502372/oily3_ngd1ag.png",
    "category": "Combination Skin"
  },
  {
    "id": 9,
    "name": "Multi-Action Serum",
    "description": "A serum that works on both hydration and oil control for combination skin.",
    "price": "₹799",
    "rating": 4.3,
    "image": "https://res.cloudinary.com/djbjfsshe/image/upload/v1747502374/oily4_bk9wtf.png",
    "category": "Combination Skin"
  },
  {
    "id": 10,
    "name": "Exfoliating Scrub",
    "description": "An exfoliator that works gently for combination skin, balancing both oil and dryness.",
    "price": "₹499",
    "rating": 4.6,
    "image": "https://res.cloudinary.com/djbjfsshe/image/upload/v1747502377/oily5_k4zibr.png",
    "category": "Combination Skin"
  },
  {
    "id": 11,
    "name": "Matte Sunscreen",
    "description": "A sunscreen with a matte finish, perfect for combination skin.",
    "price": "₹599",
    "rating": 4.0,
    "image": "https://res.cloudinary.com/djbjfsshe/image/upload/v1747502347/oily1_uifsra.png",
    "category": "Combination Skin"
  },
  {
    "id": 12,
    "name": "Gentle Skin Cleanser",
    "description": "A cleanser designed to gently clean sensitive skin without irritation.",
    "price": "₹499",
    "rating": 4.4,
    "image": "https://res.cloudinary.com/djbjfsshe/image/upload/v1747502372/oily2_p54dfq.png",
    "category": "Sensitive Skin"
  },
  {
    "id": 13,
    "name": "Calm & Soothe Moisturizer",
    "description": "Moisturizes and calms sensitive skin.",
    "price": "₹699",
    "rating": 4.4,
    "image": "https://res.cloudinary.com/djbjfsshe/image/upload/v1747502372/oily3_ngd1ag.png",
    "category": "Sensitive Skin"
  },
  {
    "id": 14,
    "name": "Soothing Serum",
    "description": "A serum that soothes irritated skin.",
    "price": "₹799",
    "rating": 4.4,
    "image": "https://res.cloudinary.com/djbjfsshe/image/upload/v1747502374/oily4_bk9wtf.png",
    "category": "Sensitive Skin"
  },
  {
    "id": 15,
    "name": "Mild Exfoliator",
    "description": "A gentle exfoliant that doesn’t irritate sensitive skin.",
    "price": "₹499",
    "rating": 4.4,
    "image": "https://res.cloudinary.com/djbjfsshe/image/upload/v1747502377/oily5_k4zibr.png",
    "category": "Sensitive Skin"
  },
  {
    "id": 16,
    "name": "Gentle Sunscreen",
    "description": "A sunscreen formulated for sensitive skin that provides protection without irritation.",
    "price": "₹599",
    "rating": 4.4,
    "image": "https://res.cloudinary.com/djbjfsshe/image/upload/v1747502347/oily1_uifsra.png",
    "category": "Sensitive Skin"
  },
  {
    "id": 17,
    "name": "Fresh Face Cleanser",
    "description": "A cleanser that removes oil and leaves the skin feeling fresh.",
    "price": "₹399",
    "rating": 4.3,
    "image": "https://res.cloudinary.com/djbjfsshe/image/upload/v1747502372/oily2_p54dfq.png",
    "category": "Oily Skin"
  },
  {
    "id": 18,
    "name": "Oil-Free Moisturizer",
    "description": "A lightweight moisturizer that hydrates without adding excess oil.",
    "price": "₹599",
    "rating": 4.3,
    "image": "https://res.cloudinary.com/djbjfsshe/image/upload/v1747502372/oily3_ngd1ag.png",
    "category": "Oily Skin"
  },
  {
    "id": 19,
    "name": "Clear Skin Serum",
    "description": "Targets excess oil and helps clear acne-prone skin.",
    "price": "₹799",
    "rating": 4.3,
    "image": "https://res.cloudinary.com/djbjfsshe/image/upload/v1747502374/oily4_bk9wtf.png",
    "category": "Oily Skin"
  },
  {
    "id": 20,
    "name": "Pore-Refining Exfoliator",
    "description": "A scrub that removes dead skin and refines pores, helping with oily skin.",
    "price": "₹499",
    "rating": 4.3,
    "image": "https://res.cloudinary.com/djbjfsshe/image/upload/v1747502347/oily1_uifsra.png",
    "category": "Oily Skin"
  },
  {
    "id": 21,
    "name": "Shine-Free Sunscreen",
    "description": "A non-greasy sunscreen that keeps shine at bay.",
    "price": "₹599",
    "rating": 4.3,
    "image": "https://res.cloudinary.com/djbjfsshe/image/upload/v1747502372/oily2_p54dfq.png",
    "category": "Oily Skin"
  },
  {
    "id": 22,
    "name": "Mattifying Primer",
    "description": "Prepares the skin for makeup by controlling oil and shine.",
    "price": "₹699",
    "rating": 4.3,
    "image": "https://res.cloudinary.com/djbjfsshe/image/upload/v1747502372/oily3_ngd1ag.png",
    "category": "Oily Skin"
  },
  {
    "id": 23,
    "name": "Deep Cleansing Mask",
    "description": "A mask that deeply cleanses pores and absorbs excess oil.",
    "price": "₹499",
    "rating": 4.3,
    "image": "https://res.cloudinary.com/djbjfsshe/image/upload/v1747502374/oily4_bk9wtf.png",
    "category": "Oily Skin"
  },
  {
    "id": 24,
    "name": "Soothing Toner",
    "description": "A toner that calms the skin while keeping it oil-free.",
    "price": "₹399",
    "rating": 4.3,
    "image": "https://res.cloudinary.com/djbjfsshe/image/upload/v1747502377/oily5_k4zibr.png",
    "category": "Oily Skin"
  }
]
